auto_profiler/__init__.py
auto_profiler/profiler.py
auto_profiler/timer.py
auto_profiler/tree.py
auto_profiler/ui.py
auto_profiler/utils.py
auto_profiler/contrib/__init__.py
auto_profiler/contrib/flask.py
auto_profiler-2.0.dist-info/METADATA
auto_profiler-2.0.dist-info/WHEEL
auto_profiler-2.0.dist-info/top_level.txt
auto_profiler-2.0.dist-info/RECORD
