Metadata-Version: 2.1
Name: auto-profiler
Version: 2.0
Summary: A realtime timer for profiling a Python function or snippet.
Home-page: https://github.com/modaresimr/auto_profiler
Author: modaresi mr
Author-email: modaresimr+git@gmail.com
License: MIT
Keywords: Profiling,Timer,Python,Auto prfiling,line profiler
Classifier: Programming Language :: Python :: 3
Classifier: License :: OSI Approved :: MIT License
Classifier: Operating System :: OS Independent
Requires-Dist: monotonic (>=1.3)
Requires-Dist: six (>=1.10.0)
Requires-Dist: tree-format (==0.1.2)
Requires-Dist: ipytree
Requires-Dist: numpy
